ticktick_sdk/__init__.py
ticktick_sdk/auth_cli.py
ticktick_sdk/cli.py
ticktick_sdk/constants.py
ticktick_sdk/exceptions.py
ticktick_sdk/server.py
ticktick_sdk/settings.py
ticktick_sdk/api/__init__.py
ticktick_sdk/api/base.py
ticktick_sdk/api/v1/__init__.py
ticktick_sdk/api/v1/auth.py
ticktick_sdk/api/v1/client.py
ticktick_sdk/api/v1/types.py
ticktick_sdk/api/v2/__init__.py
ticktick_sdk/api/v2/auth.py
ticktick_sdk/api/v2/client.py
ticktick_sdk/api/v2/types.py
ticktick_sdk/client/__init__.py
ticktick_sdk/client/client.py
ticktick_sdk/models/__init__.py
ticktick_sdk/models/base.py
ticktick_sdk/models/habit.py
ticktick_sdk/models/project.py
ticktick_sdk/models/tag.py
ticktick_sdk/models/task.py
ticktick_sdk/models/user.py
ticktick_sdk/tools/__init__.py
ticktick_sdk/tools/formatting.py
ticktick_sdk/tools/inputs.py
ticktick_sdk/unified/__init__.py
ticktick_sdk/unified/api.py
ticktick_sdk/unified/router.py
ticktick_sdk-0.4.3.dist-info/METADATA
ticktick_sdk-0.4.3.dist-info/WHEEL
ticktick_sdk-0.4.3.dist-info/entry_points.txt
ticktick_sdk-0.4.3.dist-info/licenses/LICENSE.md
ticktick_sdk-0.4.3.dist-info/RECORD
