Metadata-Version: 2.4
Name: ticktick-sdk
Version: 0.4.3
Summary: A comprehensive async Python SDK for TickTick with MCP server support
Project-URL: Homepage, https://github.com/dev-mirzabicer/ticktick-sdk
Project-URL: Repository, https://github.com/dev-mirzabicer/ticktick-sdk
Project-URL: Documentation, https://github.com/dev-mirzabicer/ticktick-sdk#readme
Project-URL: Issues, https://github.com/dev-mirzabicer/ticktick-sdk/issues
Author: dev-mirzabicer
License-Expression: MIT
License-File: LICENSE.md
Keywords: ai-assistant,api,async,gtd,mcp,model-context-protocol,productivity,task-management,ticktick,todo
Classifier: Development Status :: 4 - Beta
Classifier: Framework :: AsyncIO
Classifier: Intended Audience :: Developers
Classifier: License :: OSI Approved :: MIT License
Classifier: Programming Language :: Python :: 3
Classifier: Programming Language :: Python :: 3.11
Classifier: Programming Language :: Python :: 3.12
Classifier: Programming Language :: Python :: 3.13
Classifier: Topic :: Office/Business :: Scheduling
Classifier: Topic :: Software Development :: Libraries :: Python Modules
Classifier: Typing :: Typed
Requires-Python: >=3.11
Requires-Dist: httpx>=0.27.0
Requires-Dist: mcp>=1.0.0
Requires-Dist: pydantic-settings>=2.0.0
Requires-Dist: pydantic>=2.0.0
Provides-Extra: dev
Requires-Dist: freezegun>=1.2.0; extra == 'dev'
Requires-Dist: mypy>=1.8.0; extra == 'dev'
Requires-Dist: pytest-asyncio>=0.23.0; extra == 'dev'
Requires-Dist: pytest-cov>=4.0.0; extra == 'dev'
Requires-Dist: pytest-mock>=3.12.0; extra == 'dev'
Requires-Dist: pytest>=8.0.0; extra == 'dev'
Requires-Dist: python-dotenv>=1.0.0; extra == 'dev'
Requires-Dist: respx>=0.21.0; extra == 'dev'
Requires-Dist: ruff>=0.2.0; extra == 'dev'
